random_prompt/__init__.py
random_prompt/random_prompt.py
random_prompt/configs/random_prompt.json
random_prompt-2022.11.26.2.dist-info/LICENSE
random_prompt-2022.11.26.2.dist-info/METADATA
random_prompt-2022.11.26.2.dist-info/WHEEL
random_prompt-2022.11.26.2.dist-info/top_level.txt
random_prompt-2022.11.26.2.dist-info/zip-safe
random_prompt-2022.11.26.2.dist-info/RECORD
