Metadata-Version: 2.1
Name: random-prompt
Version: 2022.11.26.2
Summary: Random Prompt
Home-page: UNKNOWN
Author: Sergei Belousov aka BeS
Author-email: sergei.o.belousov@gmail.com
License: UNKNOWN
Platform: UNKNOWN
Classifier: Programming Language :: Python :: 3
License-File: LICENSE
